{
  "app_name": "unknown",
  "window_title": "",
  "process_name": "",
  "url": "",
  "timestamp": "2025-05-05T08:50:38.365796",
  "form_fields": [
    {
      "FieldId": "905,917,111,25",
      "FieldType": "Unknown Field",
      "Content": "Dale Camegie",
      "ApplicationName": "Unknown",
      "WindowTitle": "Unknown",
      "URL": "Unknown",
      "ProcessName": "Unknown"
    },
    {
      "FieldId": "395,678,134,21",
      "FieldType": "Unknown Field",
      "Content": "em Bravo (G:)",
      "ApplicationName": "Unknown",
      "WindowTitle": "Unknown",
      "URL": "Unknown",
      "ProcessName": "Unknown"
    },
    {
      "FieldId": "422,654,81,20",
      "FieldType": "Unknown Field",
      "Content": "iy Alpha (C:)",
      "ApplicationName": "Unknown",
      "WindowTitle": "Unknown",
      "URL": "Unknown",
      "ProcessName": "Unknown"
    },
    {
      "FieldId": "1012,594,244,44",
      "FieldType": "Password",
      "Content": "",
      "ApplicationName": "Google Chrome",
      "WindowTitle": "Log In | Robinhood - Google Chrome",
      "URL": "Unknown URL",
      "ProcessName": "chrome"
    },
    {
      "FieldId": "1012,438,290,44",
      "FieldType": "Unknown Field",
      "Content": ">.Log in.",
      "ApplicationName": "Google Chrome",
      "WindowTitle": "Log In | Robinhood - Google Chrome",
      "URL": "Unknown URL",
      "ProcessName": "chrome"
    },
    {
      "FieldId": "1314,437,290,46",
      "FieldType": "Unknown Field",
      "Content": "I Need Heip",
      "ApplicationName": "Google Chrome",
      "WindowTitle": "Log In | Robinhood - Google Chrome",
      "URL": "Unknown URL",
      "ProcessName": "chrome"
    },
    {
      "FieldId": "1011,221,594,38",
      "FieldType": "Email",
      "Content": "at@gmail.com",
      "ApplicationName": "Google Chrome",
      "WindowTitle": "Log In | Robinhood - Google Chrome",
      "URL": "Unknown URL",
      "ProcessName": "chrome"
    },
    {
      "FieldId": "863,842,193,25",
      "FieldType": "Unknown Field",
      "Content": "",
      "ApplicationName": "Google Chrome",
      "WindowTitle": "Log In | Robinhood - Google Chrome",
      "URL": "Unknown URL",
      "ProcessName": "chrome"
    },
    {
      "FieldId": "747,539,426,45",
      "FieldType": "Unknown Field",
      "Content": "",
      "ApplicationName": "Google Chrome",
      "WindowTitle": "Log In | Robinhood - Google Chrome",
      "URL": "Unknown URL",
      "ProcessName": "chrome"
    },
    {
      "FieldId": "1286,175,111,29",
      "FieldType": "Unknown Field",
      "Content": "",
      "ApplicationName": "Google Chrome",
      "WindowTitle": "Log In | Robinhood - Google Chrome",
      "URL": "Unknown URL",
      "ProcessName": "chrome"
    }
  ],
  "keystrokes": [],
  "client_ip": "46.116.189.221"
}